pypassrs-0.6.3.dist-info/METADATA
pypassrs-0.6.3.dist-info/WHEEL
pypassrs/__init__.py
pypassrs/pypassrs.pyd
pypassrs-0.6.3.dist-info/RECORD
